connector_sdk_types/__about__.py
connector_sdk_types/__init__.py
connector_sdk_types/py.typed
connector_sdk_types/generated/__init__.py
connector_sdk_types/generated/models/account_status.py
connector_sdk_types/generated/models/account_type.py
connector_sdk_types/generated/models/activate_account.py
connector_sdk_types/generated/models/activate_account200_response.py
connector_sdk_types/generated/models/activate_account_request.py
connector_sdk_types/generated/models/activate_account_response.py
connector_sdk_types/generated/models/activated_account.py
connector_sdk_types/generated/models/activity_event_type.py
connector_sdk_types/generated/models/activity_record.py
connector_sdk_types/generated/models/activity_record_activity_type.py
connector_sdk_types/generated/models/activity_record_actor.py
connector_sdk_types/generated/models/activity_record_entitlement.py
connector_sdk_types/generated/models/activity_record_target.py
connector_sdk_types/generated/models/activity_type.py
connector_sdk_types/generated/models/amount.py
connector_sdk_types/generated/models/app_category.py
connector_sdk_types/generated/models/app_info.py
connector_sdk_types/generated/models/app_info200_response.py
connector_sdk_types/generated/models/app_info_request.py
connector_sdk_types/generated/models/app_info_request_payload.py
connector_sdk_types/generated/models/app_info_response.py
connector_sdk_types/generated/models/application.py
connector_sdk_types/generated/models/application_account.py
connector_sdk_types/generated/models/application_activity_record.py
connector_sdk_types/generated/models/application_entitlement_association.py
connector_sdk_types/generated/models/application_entitlement_data.py
connector_sdk_types/generated/models/application_resource_data.py
connector_sdk_types/generated/models/application_status.py
connector_sdk_types/generated/models/assign_application.py
connector_sdk_types/generated/models/assign_application200_response.py
connector_sdk_types-0.37.0.dist-info/licenses/LICENSE.txt
connector_sdk_types-0.37.0.dist-info/METADATA
connector_sdk_types-0.37.0.dist-info/WHEEL
connector_sdk_types-0.37.0.dist-info/top_level.txt
connector_sdk_types-0.37.0.dist-info/RECORD
