Metadata-Version: 2.4
Name: connector-sdk-types
Version: 0.37.0
Summary: Generated types for the Lumos Connector SDK
Author-email: teamlumos <security@lumos.com>
License-Expression: Apache-2.0
Project-URL: Documentation, https://developers.lumos.com/reference/the-lumos-connector-api
Keywords: integrations,types
Classifier: Development Status :: 4 - Beta
Classifier: Programming Language :: Python
Classifier: Programming Language :: Python :: 3.10
Classifier: Programming Language :: Python :: 3.11
Classifier: Programming Language :: Python :: Implementation :: CPython
Classifier: Programming Language :: Python :: Implementation :: PyPy
Requires-Python: >=3.10
License-File: LICENSE.txt
Requires-Dist: pydantic<2.10,>=2
Provides-Extra: dev
Requires-Dist: pytest>=8; extra == "dev"
Requires-Dist: pytest-asyncio>=0.23; extra == "dev"
Provides-Extra: all
Requires-Dist: connector-sdk-types[dev]; extra == "all"
Dynamic: license-file
